libsesame.so
pysame.cpython-312-x86_64-linux-gnu.so
pysame.libs/libgomp-24e2ab19.so.1.0.0
pysame-0.1.0.dist-info/LICENSE
pysame-0.1.0.dist-info/top_level.txt
pysame-0.1.0.dist-info/METADATA
pysame-0.1.0.dist-info/WHEEL
pysame-0.1.0.dist-info/RECORD
