Metadata-Version: 2.1
Name: pysame
Version: 0.1.0
Summary: Stream clustering algorithms on modern hardware
Home-page: https://github.com/intellistream/Sesame
Author: Shuhao Zhang
Author-email: Zhengru Wang <wangshaun@outlook.com>
Project-URL: Homepage, https://github.com/intellistream/Sesame
Project-URL: Issues, https://github.com/intellistream/Sesame/issues
Classifier: Programming Language :: Python :: 3
Classifier: License :: OSI Approved :: MIT License
Classifier: Operating System :: OS Independent
Requires-Python: >=3.7
License-File: LICENSE
